{
  "description":"metales ordinarios",
  "metales ordinarios":[
    {
      "name":"aluminio",
      "gender":"m",
      "number":"s"
    },
    {
      "name":"acero",
      "gender":"m",
      "number":"s"
    },
    {
      "name":"alpaca",
      "gender":"f",
      "number":"s"
    },
    {
      "name":"acero inoxidable",
      "gender":"m",
      "number":"s"
    },
    {
      "name":"amalgama",
      "gender":"f",
      "number":"s"
    },
    {
      "name":"bronce",
      "gender":"m",
      "number":"s"
    },
    {
      "name":"cromo",
      "gender":"m",
      "number":"s"
    },
    {
      "name":"cobre",
      "gender":"m",
      "number":"s"
    },
    {
      "name":"estaño",
      "gender":"m",
      "number":"s"
    },
    {
      "name":"electro",
      "gender":"m",
      "number":"s"
    },
    {
      "name":"hierro",
      "gender":"m",
      "number":"s"
    },
    {
      "name":"latón",
      "gender":"f",
      "number":"s"
    },
    {
      "name":"metal blanco",
      "gender":"m",
      "number":"s"
    },
    {
      "name":"níquel",
      "gender":"m",
      "number":"s"
    },
    {
      "name":"oro",
      "gender":"m",
      "number":"s"
    },
    {
      "name":"plomo",
      "gender":"m",
      "number":"s"
    },
    {
      "name":"platino",
      "gender":"m",
      "number":"s"
    },
    {
      "name":"plata",
      "gender":"f",
      "number":"s"
    },
    {
      "name":"plata esterlina",
      "gender":"m",
      "number":"s"
    },
    {
      "name":"peltre",
      "gender":"m",
      "number":"s"
    },
    {
      "name":"titanio",
      "gender":"m",
      "number":"s"
    },
    {
      "name":"zinc",
      "gender":"m",
      "number":"s"
    }
  ]
}
